{
  "modid": "",
  "uniqueName": "Quick_Start___Taco_Tuesday",
  "saveName": "Quick_Start___Taco_Tuesday",
  "displayName": "Quick Start - Taco Tuesday",
  "displayInfo": "",
  "colorHex": "FFFFFFFF",
  "language": "en_us",
  "hasCustomIcon": true,
  "showBackground": true,
  "legacyTexture": false,
  "backgroundResource": "enchiridion:textures/books/rustic2.png",
  "BACKGROUND_START_X": -10,
  "BACKGROUND_START_Y": -10,
  "BACKGROUND_END_X": 440,
  "BACKGROUND_END_Y": 240,
  "defaultPage": 0,
  "isLocked": false,
  "forgetPageOnClose": false,
  "book": [
    {
      "features": [
        {
          "xPos": 5,
          "yPos": 15,
          "width": 180.0,
          "height": 93.0,
          "feature": {
            "class": "joshie.enchiridion.gui.book.features.FeatureText",
            "properties": {
              "text": "[b]    TACO TUESDAY",
              "size": 1.7000002
            }
          },
          "isLocked": true,
          "isHidden": false,
          "layerIndex": 0
        },
        {
          "xPos": 21,
          "yPos": 28,
          "width": 182.0,
          "height": 14.0,
          "feature": {
            "class": "joshie.enchiridion.gui.book.features.FeatureText",
            "properties": {
              "text": "          [i]QUICKSTART GUIDE[/i]",
              "size": 1.0
            }
          },
          "isLocked": false,
          "isHidden": false,
          "layerIndex": 1
        },
        {
          "xPos": 261,
          "yPos": 177,
          "width": 30.0,
          "height": 29.0,
          "feature": {
            "class": "joshie.enchiridion.gui.book.features.FeatureButton",
            "properties": {
              "action": {
                "class": "joshie.enchiridion.gui.book.buttons.actions.ActionOpenWebpage",
                "properties": {
                  "url": "https://minecraft.curseforge.com/projects/taco-tuesday?gameCategorySlug\u003dmc-mods\u0026projectID\u003d266475"
                }
              },
              "size": 1.0,
              "leftClick": true,
              "rightClick": true,
              "otherClick": false,
              "tooltip": "",
              "hoverText": "Open Wiki/Website",
              "hoverXOffset": 30,
              "hoverYOffset": 10,
              "unhoveredText": "Open Wiki/Website",
              "unhoveredXOffset": 30,
              "unhoveredYOffset": 10,
              "hoveredResource": "enchiridion:images/quick_start___minecraft/website-yes-highlight.png",
              "unhoveredResource": "enchiridion:images/quick_start___minecraft/website-yes.png"
            }
          },
          "isLocked": false,
          "isHidden": false,
          "layerIndex": 2
        },
        {
          "xPos": 229,
          "yPos": 30,
          "width": 178.0,
          "height": 71.0,
          "feature": {
            "class": "joshie.enchiridion.gui.book.features.FeatureText",
            "properties": {
              "text": "If savory tacos aren\u0027t what you are craving, then you can make some Ice Cream.\n\n\n\nAnd make an Ice Cream Taco.\n\n\n\nThere are also many magical tacos you can make with rarer ingredients. They provide a bunch of buffs for consuming them!",
              "size": 0.9
            }
          },
          "isLocked": true,
          "isHidden": false,
          "layerIndex": 3
        },
        {
          "xPos": 23,
          "yPos": 40,
          "width": 178.0,
          "height": 71.0,
          "feature": {
            "class": "joshie.enchiridion.gui.book.features.FeatureText",
            "properties": {
              "text": "Taco Tuesday adds tacos. A lot of different tacos. Some of them give you health boosts and buffs!\n\n\n\nYou start by making a Soft Tortilla. It can be used as is...\n\n\n\n...or smelted into a Crunchy Taco Shell.\n\n\n\nYou can then make Soft or Crunchy Tacos of many varieties.",
              "size": 0.9
            }
          },
          "isLocked": false,
          "isHidden": false,
          "layerIndex": 4
        },
        {
          "xPos": 102,
          "yPos": 107,
          "width": 16.0,
          "height": 16.0,
          "feature": {
            "class": "joshie.enchiridion.gui.book.features.FeatureItem",
            "properties": {
              "itemString": "tt:hard_tortilla",
              "hideTooltip": false
            }
          },
          "isLocked": false,
          "isHidden": false,
          "layerIndex": 5
        },
        {
          "xPos": 101,
          "yPos": 140,
          "width": 16.0,
          "height": 16.0,
          "feature": {
            "class": "joshie.enchiridion.gui.book.features.FeatureItem",
            "properties": {
              "itemString": "tt:hard_pork_taco",
              "hideTooltip": false
            }
          },
          "isLocked": false,
          "isHidden": false,
          "layerIndex": 6
        },
        {
          "xPos": 129,
          "yPos": 141,
          "width": 16.0,
          "height": 16.0,
          "feature": {
            "class": "joshie.enchiridion.gui.book.features.FeatureItem",
            "properties": {
              "itemString": "tt:hard_fish_taco",
              "hideTooltip": false
            }
          },
          "isLocked": false,
          "isHidden": false,
          "layerIndex": 7
        },
        {
          "xPos": 318,
          "yPos": 12,
          "width": 16.0,
          "height": 16.0,
          "feature": {
            "class": "joshie.enchiridion.gui.book.features.FeatureItem",
            "properties": {
              "itemString": "tt:plain_ice_cream",
              "hideTooltip": false
            }
          },
          "isLocked": false,
          "isHidden": false,
          "layerIndex": 8
        },
        {
          "xPos": 103,
          "yPos": 68,
          "width": 16.0,
          "height": 16.0,
          "feature": {
            "class": "joshie.enchiridion.gui.book.features.FeatureItem",
            "properties": {
              "itemString": "tt:soft_tortilla",
              "hideTooltip": false
            }
          },
          "isLocked": false,
          "isHidden": false,
          "layerIndex": 9
        },
        {
          "xPos": 74,
          "yPos": 139,
          "width": 16.0,
          "height": 16.0,
          "feature": {
            "class": "joshie.enchiridion.gui.book.features.FeatureItem",
            "properties": {
              "itemString": "tt:soft_beef_taco",
              "hideTooltip": false
            }
          },
          "isLocked": false,
          "isHidden": false,
          "layerIndex": 10
        },
        {
          "xPos": 318,
          "yPos": 54,
          "width": 16.0,
          "height": 16.0,
          "feature": {
            "class": "joshie.enchiridion.gui.book.features.FeatureItem",
            "properties": {
              "itemString": "tt:plain_ice_cream_taco",
              "hideTooltip": false
            }
          },
          "isLocked": false,
          "isHidden": false,
          "layerIndex": 11
        },
        {
          "xPos": 317,
          "yPos": 88,
          "width": 16.0,
          "height": 16.0,
          "feature": {
            "class": "joshie.enchiridion.gui.book.features.FeatureItem",
            "properties": {
              "itemString": "tt:diamond_taco",
              "hideTooltip": false
            }
          },
          "isLocked": false,
          "isHidden": false,
          "layerIndex": 12
        }
      ],
      "pageNumber": 0,
      "isScrollable": false
    }
  ]
}